agentbill_langchain/__init__.py
agentbill_langchain/callback.py
agentbill_langchain-1.0.0.dist-info/METADATA
agentbill_langchain-1.0.0.dist-info/WHEEL
agentbill_langchain-1.0.0.dist-info/top_level.txt
agentbill_langchain-1.0.0.dist-info/RECORD
