Metadata-Version: 2.4
Name: agentbill-langchain
Version: 1.0.0
Summary: LangChain integration for AgentBill
Author: AgentBill
Requires-Python: >=3.8
Requires-Dist: langchain>=0.1.0
Requires-Dist: requests>=2.28.0
Dynamic: author
Dynamic: requires-dist
Dynamic: requires-python
Dynamic: summary
